{"cases": [{"backend": "tp_ep_launcher_http", "coalesced_batch_max": 32, "coalesced_batches": 1, "compose_copy_ms": 297.258583, "compose_final_ms": 179.992708, "compose_ms": 541.86712, "compose_reduce_ms": 64.615829, "continuation_tok_s": 808.9824228132052, "continuation_tok_s_decode": 1062.8272944913206, "continuation_tokens": 992, "ctx": 262144, "dense_ms": 0.0, "elapsed_s": 1.348272391, "ep_ms": 490.663413, "generated_tok_s": 759.49044631887, "generated_tok_s_decode": 991.4057504327664, "generated_tokens": 1024, "generation_requests": 32, "gpu_mem_used_max_mib": 13184.0, "gpu_util_avg": 9.15, "gpu_util_max": 32.0, "request_token_pattern": "32", "schema": "ds4_v100_tp_ep_sustained_http_case.v3", "slots": 32, "status_200": 32, "token_match": 32, "token_mismatch": 0, "tokens_per_request": 32}], "schema": "ds4_v100_tp_ep_sustained_http.v3"}
